ct2vl/__init__.py
ct2vl/__main__.py
ct2vl/cli.py
ct2vl/conversion.py
ct2vl/rates.py
ct2vl-1.0.4.dist-info/LICENSE
ct2vl-1.0.4.dist-info/METADATA
ct2vl-1.0.4.dist-info/WHEEL
ct2vl-1.0.4.dist-info/top_level.txt
ct2vl-1.0.4.dist-info/RECORD
