Metadata-Version: 2.1
Name: ct2vl
Version: 1.0.4
Summary: Converting SARS-CoV-2 PCR test Ct values to viral loads
Home-page: https://github.com/Elliot-D-Hill/ct2vl
Author: Elliot Hill, Ramy Arnaout, Cody Callahan
Author-email: rarnaout@bidmc.harvar.edu
Project-URL: Bug Tracker, https://github.com/Elliot-D-Hill/ct2vl/issues
Classifier: Programming Language :: Python :: 3
Classifier: License :: OSI Approved :: MIT License
Classifier: Operating System :: OS Independent
Requires-Python: >=3.7
License-File: LICENSE
Requires-Dist: pandas (>=1.3.0)
Requires-Dist: numpy (>=1.21.5)
Requires-Dist: scipy (>=1.7.0)
Requires-Dist: scikit-learn (>=1.0.2)
